nameko_extras/__init__.py
nameko_extras/autoreload.py
nameko_extras/cli_commands.py
nameko_extras/cli/__init__.py
nameko_extras/cli/main.py
nameko_extras/cli/run.py
nameko_extras-0.1.1.dist-info/DESCRIPTION.rst
nameko_extras-0.1.1.dist-info/METADATA
nameko_extras-0.1.1.dist-info/RECORD
nameko_extras-0.1.1.dist-info/WHEEL
nameko_extras-0.1.1.dist-info/entry_points.txt
nameko_extras-0.1.1.dist-info/metadata.json
nameko_extras-0.1.1.dist-info/top_level.txt
